googletrends/__init__.py
googletrends/examples.py
googletrends/googletrends.py
googletrends/data/__init__.py
googletrends/data/corona_all_countries.zip
googletrends/data/country_and_code.zip
googletrends/utils/__init__.py
googletrends/utils/check_connection.py
googletrends-0.1.2.dist-info/LICENSE
googletrends-0.1.2.dist-info/METADATA
googletrends-0.1.2.dist-info/WHEEL
googletrends-0.1.2.dist-info/top_level.txt
googletrends-0.1.2.dist-info/RECORD
