Metadata-Version: 2.1
Name: googletrends
Version: 0.1.2
Summary: Python package to examine trending, spatio and temporal google searching for input queries.
Home-page: https://erdogant.github.io/googletrends
Download-URL: https://github.com/erdogant/googletrends/archive/0.1.2.tar.gz
Author: Erdogan Taskesen
Author-email: erdogant@gmail.com
Classifier: Programming Language :: Python :: 3
Classifier: License :: OSI Approved :: MIT License
Classifier: Operating System :: OS Independent
Requires-Python: >=3
License-File: LICENSE
Requires-Dist: pytrends
Requires-Dist: matplotlib
Requires-Dist: numpy
Requires-Dist: pandas
Requires-Dist: worldmap
Requires-Dist: scikit-learn
Requires-Dist: colourmap
Requires-Dist: scipy
